ctk_listbox/__init__.py
ctk_listbox/ctk_listbox.py
ctk_listbox_typed-1.5.0.dist-info/LICENSE
ctk_listbox_typed-1.5.0.dist-info/METADATA
ctk_listbox_typed-1.5.0.dist-info/WHEEL
ctk_listbox_typed-1.5.0.dist-info/top_level.txt
ctk_listbox_typed-1.5.0.dist-info/RECORD
