Metadata-Version: 2.1
Name: ctk_listbox_typed
Version: 1.5.0
Summary: Customtkinter Listbox widget (with typing)
Author: Akash Bora
Author-email: melektron <matteo@elektron.work>
Project-URL: Homepage, https://github.com/melektron/ctk_listbox
Project-URL: Issues, https://github.com/melektron/ctk_listbox/issues
Classifier: Programming Language :: Python :: 3.12
Classifier: License :: OSI Approved :: MIT License
Classifier: Operating System :: OS Independent
Requires-Python: >=3.12
License-File: LICENSE
